{"VCALENDAR":
  {"PRODID":{"value":"-//RDU Software//NONSGML HandCal//EN"},
   "VERSION":{"value":"2.0"},
   "VTIMEZONE":
    {"TZID":{"value":"America/New_York"},
     "STANDARD":
      {"DTSTART":
        {"value":
          {"year":"1998",
           "month":"10",
           "day":"25",
           "hour":"02",
           "min":"00",
           "sec":"00",
           "zone":"America/New_York"}},
       "TZOFFSETFROM":{"value":{"sign":"-", "hr":"04", "min":"00"}},
       "TZOFFSETTO":{"value":{"sign":"-", "hr":"05", "min":"00"}},
       "TZNAME":{"value":"EST"}},
     "DAYLIGHT":
      {"DTSTART":
        {"value":
          {"year":"1999",
           "month":"04",
           "day":"04",
           "hour":"02",
           "min":"00",
           "sec":"00",
           "zone":"America/New_York"}},
       "TZOFFSETFROM":{"value":{"sign":"-", "hr":"05", "min":"00"}},
       "TZOFFSETTO":{"value":{"sign":"-", "hr":"04", "min":"00"}},
       "TZNAME":{"value":"EDT"}}},
   "VEVENT":
    {"DTSTAMP":
      {"value":
        {"year":"1998",
         "month":"03",
         "day":"09",
         "hour":"23",
         "min":"10",
         "sec":"00"}},
     "UID":{"value":"guid-1.example.com"},
     "ORGANIZER":{"value":"mailto:mrbig@example.com"},
     "ATTENDEE":
      {"value":"mailto:employee-A@example.com",
       "params":{"RSVP":true, "ROLE":"REQ-PARTICIPANT", "CUTYPE":"GROUP"}},
     "DESCRIPTION":{"value":"Project XYZ Review Meeting"},
     "CATEGORIES":{"value":["MEETING"]},
     "CLASS":{"value":"PUBLIC"},
     "CREATED":
      {"value":
        {"year":"1998",
         "month":"03",
         "day":"09",
         "hour":"13",
         "min":"00",
         "sec":"00"}},
     "SUMMARY":{"value":"XYZ Project Review"},
     "DTSTART":
      {"value":
        {"year":"1998",
         "month":"03",
         "day":"12",
         "hour":"08",
         "min":"30",
         "sec":"00",
         "zone":"America/New_York"},
       "params":{"TZID":"America/New_York"}},
     "DTEND":
      {"value":
        {"year":"1998",
         "month":"03",
         "day":"12",
         "hour":"09",
         "min":"30",
         "sec":"00",
         "zone":"America/New_York"},
       "params":{"TZID":"America/New_York"}},
     "LOCATION":{"value":"1CP Conference Room 4350"}}}}
